xnLinkFinder/__init__.py
xnLinkFinder/xnLinkFinder.py
xnlinkfinder-8.1.dist-info/licenses/LICENSE
xnlinkfinder-8.1.dist-info/METADATA
xnlinkfinder-8.1.dist-info/WHEEL
xnlinkfinder-8.1.dist-info/entry_points.txt
xnlinkfinder-8.1.dist-info/top_level.txt
xnlinkfinder-8.1.dist-info/RECORD
