Metadata-Version: 2.4
Name: xnlinkfinder
Version: 8.1
Summary: A python script to find endpoints from a URL, a file of URLs, a directory of files, a Burp XML file or a ZAP ASCII message file. It also gets potential parameters and a target specific wordlist.
Home-page: https://github.com/xnl-h4ck3r/xnlLinkFinder
Author: @xnl-h4ck3r
License-File: LICENSE
Requires-Dist: requests
Requires-Dist: psutil
Requires-Dist: pyyaml
Requires-Dist: termcolor
Requires-Dist: urlparse3
Requires-Dist: beautifulsoup4
Requires-Dist: lxml
Requires-Dist: html5lib
Requires-Dist: urllib3
Requires-Dist: tldextract
Requires-Dist: inflect>=7.3.0
Requires-Dist: playwright
Requires-Dist: pypdf
Dynamic: author
Dynamic: description
Dynamic: description-content-type
Dynamic: home-page
Dynamic: license-file
Dynamic: requires-dist
Dynamic: summary
